slpso/__init__.py
slpso/algorithm.py
slpso/slpso.py
slpso-0.1.2.dist-info/LICENSE
slpso-0.1.2.dist-info/METADATA
slpso-0.1.2.dist-info/WHEEL
slpso-0.1.2.dist-info/RECORD
