Metadata-Version: 2.1
Name: slpso
Version: 0.1.2
Summary: 
Author: viniciusGomes
Author-email: vsg.dev.tech@gmail.com
Requires-Python: >=3.8,<4.0
Classifier: Programming Language :: Python :: 3
Classifier: Programming Language :: Python :: 3.8
Classifier: Programming Language :: Python :: 3.9
Classifier: Programming Language :: Python :: 3.10
Classifier: Programming Language :: Python :: 3.11
Requires-Dist: numpy (>=1.23.5,<2.0.0)
